querysquirrel/__init__.py
querysquirrel/myfunctions.py
tests/__init__.py
tests/test_myfunctions.py
querysquirrel-0.1.13.dist-info/LICENSE
querysquirrel-0.1.13.dist-info/METADATA
querysquirrel-0.1.13.dist-info/WHEEL
querysquirrel-0.1.13.dist-info/top_level.txt
querysquirrel-0.1.13.dist-info/RECORD
